asce7/__init__.py
asce7/common.py
asce7/exceptions.py
asce7/outline.md
asce7/types.py
asce7/v2016/__init__.py
asce7/v2016/chapter1.py
asce7/v2016/chapter11.py
asce7/v2016/chapter12.py
asce7/v2016/chapter13.py
asce7/v2016/chapter15.py
asce7/v2016/chapter2.py
asce7/v2016/chapter26.py
asce7/v2016/chapter27.py
asce7/v2016/chapter28.py
asce7/v2016/chapter29.py
asce7/v2016/chapter30.py
asce7/v2016/chapter7.py
asce7-0.1.dist-info/LICENSE
asce7-0.1.dist-info/WHEEL
asce7-0.1.dist-info/METADATA
asce7-0.1.dist-info/RECORD
