Metadata-Version: 2.1
Name: asce7
Version: 0.1
Summary: Implementation of the ASCE 7 building code.
Author-email: Ricky L Teachey Jr <ricky@teachey.org>
Requires-Python: >=3.9
Classifier: Intended Audience :: Other Audience
Classifier: License :: OSI Approved :: MIT License
Classifier: Programming Language :: Python :: 3
Classifier: Topic :: Scientific/Engineering
Classifier: Development Status :: 2 - Pre-Alpha
Requires-Dist: numpy >=1.20
Requires-Dist: scipy >=1.7
Requires-Dist: ceng
Requires-Dist: pytest >=6.2 ; extra == "test"
Project-URL: Home, https://github.com/ricyteach/asce7
Provides-Extra: test
